{"SURVIVAL":{"enderChestContents":{},"inventoryContents":{},"offHandItem":{"==":"org.bukkit.inventory.ItemStack","v":3700,"type":"AIR","amount":0},"potions":[{"==":"PotionEffect","effect":"minecraft:weakness","duration":199,"amplifier":10,"ambient":false,"has-particles":false,"has-icon":false}],"lastLocation":{"==":"org.bukkit.Location","world":"world","x":120.51249694824219,"y":65.0,"z":-15.699999809265137,"pitch":11.849975,"yaw":-96.44507},"bedSpawnLocation":{"==":"org.bukkit.Location","world":"world","x":542.5,"y":86.0999984741211,"z":-960.5,"pitch":0.0,"yaw":-15.040649},"armorContents":{},"stats":{"ex":"2.5610034","ma":"300","fl":"17","el":"0","xp":"0.0","hp":"17.66666603088379","txp":"0","ft":"-20","sa":"0.0","fd":"0.0","ra":"300"}}}